examples/__init__.py
examples/data_util.py
examples/utils.py
slapo/__init__.py
slapo/build.py
slapo/checkpoint.py
slapo/env.py
slapo/initialization.py
slapo/logger.py
slapo/pattern.py
slapo/pipeline.py
slapo/random.py
slapo/schedule.py
slapo/tracer.py
slapo/version.py
slapo/autotune/__init__.py
slapo/autotune/tune.py
slapo/framework_dialect/__init__.py
slapo/framework_dialect/registry.py
slapo/framework_dialect/deepspeed/__init__.py
slapo/framework_dialect/deepspeed/engine.py
slapo/framework_dialect/deepspeed/pipeline.py
slapo/framework_dialect/deepspeed/utils.py
slapo/framework_dialect/megatron/__init__.py
slapo/framework_dialect/megatron/utils.py
slapo/model_schedule/__init__.py
slapo/model_schedule/albert.py
slapo/model_schedule/api.py
slapo/model_schedule/bert.py
slapo/model_schedule/gpt2.py
slapo/model_schedule/gpt_neo.py
slapo/model_schedule/opt.py
slapo/model_schedule/registry.py
slapo/model_schedule/roberta.py
slapo/model_schedule/t5.py
slapo/model_schedule/wideresnet.py
slapo/op/__init__.py
slapo/op/attention.py
slapo/op/cross_entropy.py
slapo/op/fused_bias.py
slapo/op/linear.py
slapo/op/mlp.py
slapo/op/utils.py
slapo/primitives/__init__.py
slapo/primitives/annotate.py
slapo/primitives/base.py
slapo/primitives/checkpoint.py
slapo/primitives/fusion.py
slapo/primitives/pipeline.py
slapo/primitives/replace.py
slapo/primitives/tensor_parallel.py
slapo/sharding/__init__.py
slapo/sharding/shard_ops.py
slapo/sharding/sync_ops.py
slapo/utils/__init__.py
slapo/utils/common.py
slapo/utils/mapping.py
slapo/utils/report.py
slapo/utils/versions.py
tests/__init__.py
tests/end2end.py
tests/test_annotate.py
tests/test_checkpoint.py
tests/test_consolidation.py
tests/test_fork_rng.py
tests/test_fusion.py
tests/test_op.py
tests/test_pipeline_partition.py
tests/test_random.py
tests/test_replace.py
tests/test_shard.py
tests/test_shard_sync_op.py
tests/test_subgraph.py
tests/test_trace.py
tests/utils.py
slapo-0.0.3.dist-info/LICENSE
slapo-0.0.3.dist-info/METADATA
slapo-0.0.3.dist-info/WHEEL
slapo-0.0.3.dist-info/top_level.txt
slapo-0.0.3.dist-info/zip-safe
slapo-0.0.3.dist-info/RECORD
