Metadata-Version: 2.1
Name: slapo
Version: 0.0.3
Summary: Slapo: A Schedule Language for Progressive Optimization.
Home-page: https://github.com/awslabs/slapo
Author: Slapo Community
Classifier: Programming Language :: Python :: 3.7
Classifier: Programming Language :: Python :: 3.8
Classifier: Programming Language :: Python :: 3.9
Classifier: Programming Language :: Python :: 3.10
Classifier: Topic :: Scientific/Engineering :: Artificial Intelligence
Classifier: Operating System :: OS Independent
Requires-Python: >=3.7
License-File: LICENSE
Requires-Dist: packaging
Requires-Dist: psutil
